prolm/__init__.py
prolm/prolm_tokenizer.py
prolm/data/aas.txt
prolm/data/cds.txt
prolm/data/ncds.txt
prolm/data/vocab.txt
prolm/model/__init__.py
prolm/model/configuration_prolm.py
prolm/model/modeling_prolm.py
prolm/models/__init__.py
prolm/models/prolm1/__init__.py
prolm/models/prolm1/configuration_prolm.py
prolm/models/prolm1/modeling_prolm.py
prolm/models/prolm2/__init__.py
prolm/models/prolm2/configuration_prolm.py
prolm/models/prolm2/modeling_prolm.py
prolm-0.1.1.dist-info/LICENSE
prolm-0.1.1.dist-info/METADATA
prolm-0.1.1.dist-info/WHEEL
prolm-0.1.1.dist-info/top_level.txt
prolm-0.1.1.dist-info/RECORD
